<?xml version="1.0" encoding="UTF-8"?>
<list enabled="true" xmlns:xsi="http://www.w3.org/2001/XMLSchema-instance" xsi:noNamespaceSchemaLocation="../../xsd/spawns.xsd">
	<spawn name="22_18">
		<npc id="27096" x="69580" y="10394" z="-3692" heading="0" respawnDelay="180" /> <!-- Singing Flower Nightmare -->
		<npc id="27096" x="69781" y="10394" z="-3692" heading="0" respawnDelay="180" /> <!-- Singing Flower Nightmare -->
		<npc id="27096" x="69883" y="10928" z="-3692" heading="0" respawnDelay="180" /> <!-- Singing Flower Nightmare -->
		<npc id="30738" x="69836" y="18108" z="-3664" heading="0" respawnDelay="60" /> <!-- Matild -->
		<npc id="30757" x="95348" y="22298" z="-2882" heading="0" respawnDelay="60" /> <!-- Statue Of Offering -->
		<npc id="30759" x="95359" y="22208" z="-2879" heading="4096" respawnDelay="60" /> <!-- Kalis -->
		<npc id="30934" x="85881" y="14126" z="-5257" heading="46752" respawnDelay="60" /> <!-- Marsha -->
		<npc id="30935" x="82234" y="22257" z="-5257" heading="54112" respawnDelay="60" /> <!-- Trumpin -->
	</spawn>
</list>
